adafruit_as5600.py
adafruit_circuitpython_as5600-1.0.1.dist-info/licenses/LICENSE
adafruit_circuitpython_as5600-1.0.1.dist-info/METADATA
adafruit_circuitpython_as5600-1.0.1.dist-info/WHEEL
adafruit_circuitpython_as5600-1.0.1.dist-info/top_level.txt
adafruit_circuitpython_as5600-1.0.1.dist-info/RECORD
